ipython_unittest/__init__.py
ipython_unittest/dojo.py
ipython_unittest/magics.py
ipython_unittest-0.3.2.dist-info/LICENSE
ipython_unittest-0.3.2.dist-info/METADATA
ipython_unittest-0.3.2.dist-info/WHEEL
ipython_unittest-0.3.2.dist-info/top_level.txt
ipython_unittest-0.3.2.dist-info/RECORD
