Metadata-Version: 2.1
Name: ipython-unittest
Version: 0.3.2
Summary: Add unittest cell magics to IPython for easily running tests
Author-email: Joao Pimentel <joaofelipenp@gmail.com>
License: MIT License
Project-URL: Source, https://github.com/JoaoFelipe/ipython-unittest
Keywords: ipython,jupyter,unittest,tdd,dojo
Classifier: Programming Language :: Python :: 3
Classifier: License :: OSI Approved :: MIT License
Classifier: Operating System :: OS Independent
License-File: LICENSE
Requires-Dist: ipython
Provides-Extra: unparse
Requires-Dist: astor ; extra == 'unparse'
